[
    {
        "image_url": "http://bhoomi.csa.iisc.ernet.in:8080/ihg/manuscript_editor/images/AAVARNI%20VYAKHYA/GOML/991/26.jpg",
        "label": "Decorator",
        "instance_id": "http://bhoomi.csa.iisc.ernet.in:8080/ihg/manuscript_editor/images/AAVARNI%20VYAKHYA/GOML/991/26.jpg-1_1",
        "image_id": "http://bhoomi.csa.iisc.ernet.in:8080/ihg/manuscript_editor/images/AAVARNI%20VYAKHYA/GOML/991/26.jpg-1",
        "bbox": [
            79,
            52,
            104,
            71
        ],
        "components": [
            {
                "bbox": [
                    79,
                    52,
                    104,
                    71
                ],
                "poly": [
                    [
                        165,
                        79
                    ],
                    [
                        121,
                        52
                    ],
                    [
                        96,
                        70
                    ],
                    [
                        79,
                        86
                    ],
                    [
                        112,
                        115
                    ],
                    [
                        147,
                        122
                    ],
                    [
                        171,
                        113
                    ],
                    [
                        178,
                        103
                    ],
                    [
                        182,
                        93
                    ],
                    [
                        176,
                        86
                    ],
                    [
                        147,
                        77
                    ]
                ],
                "area": 11316.5
            }
        ],
        "split": "train"
    },
    {
        "image_url": "http://bhoomi.csa.iisc.ernet.in:8080/ihg/manuscript_editor/images/AAVARNI%20VYAKHYA/GOML/991/26.jpg",
        "label": "Character Line Segment",
        "instance_id": "http://bhoomi.csa.iisc.ernet.in:8080/ihg/manuscript_editor/images/AAVARNI%20VYAKHYA/GOML/991/26.jpg-1_2",
        "image_id": "http://bhoomi.csa.iisc.ernet.in:8080/ihg/manuscript_editor/images/AAVARNI%20VYAKHYA/GOML/991/26.jpg-1",
        "bbox": [
            217,
            23,
            2071,
            74
        ],
        "components": [
            {
                "bbox": [
                    217,
                    23,
                    2071,
                    74
                ],
                "poly": [
                    [
                        229,
                        29
                    ],
                    [
                        322,
                        26
                    ],
                    [
                        342,
                        23
                    ],
                    [
                        344,
                        29
                    ],
                    [
                        420,
                        39
                    ],
                    [
                        563,
                        39
                    ],
                    [
                        621,
                        36
                    ],
                    [
                        701,
                        38
                    ],
                    [
                        776,
                        39
                    ],
                    [
                        841,
                        39
                    ],
                    [
                        862,
                        31
                    ],
                    [
                        872,
                        42
                    ],
                    [
                        966,
                        42
                    ],
                    [
                        1071,
                        42
                    ],
                    [
                        1174,
                        47
                    ],
                    [
                        1187,
                        36
                    ],
                    [
                        1224,
                        49
                    ],
                    [
                        1315,
                        42
                    ],
                    [
                        1455,
                        42
                    ],
                    [
                        1564,
                        42
                    ],
                    [
                        1619,
                        42
                    ],
                    [
                        1767,
                        40
                    ],
                    [
                        1845,
                        38
                    ],
                    [
                        1911,
                        30
                    ],
                    [
                        1929,
                        27
                    ],
                    [
                        1931,
                        36
                    ],
                    [
                        2016,
                        35
                    ],
                    [
                        2098,
                        31
                    ],
                    [
                        2132,
                        33
                    ],
                    [
                        2162,
                        38
                    ],
                    [
                        2201,
                        39
                    ],
                    [
                        2282,
                        39
                    ],
                    [
                        2287,
                        67
                    ],
                    [
                        2283,
                        86
                    ],
                    [
                        2126,
                        87
                    ],
                    [
                        2028,
                        80
                    ],
                    [
                        1899,
                        85
                    ],
                    [
                        1867,
                        90
                    ],
                    [
                        1797,
                        90
                    ],
                    [
                        1708,
                        88
                    ],
                    [
                        1579,
                        88
                    ],
                    [
                        1451,
                        88
                    ],
                    [
                        1442,
                        89
                    ],
                    [
                        1398,
                        96
                    ],
                    [
                        1297,
                        95
                    ],
                    [
                        1205,
                        94
                    ],
                    [
                        1121,
                        92
                    ],
                    [
                        987,
                        85
                    ],
                    [
                        899,
                        78
                    ],
                    [
                        852,
                        79
                    ],
                    [
                        778,
                        80
                    ],
                    [
                        700,
                        81
                    ],
                    [
                        677,
                        88
                    ],
                    [
                        363,
                        70
                    ],
                    [
                        285,
                        74
                    ],
                    [
                        222,
                        70
                    ],
                    [
                        217,
                        66
                    ]
                ],
                "area": 245702.0
            }
        ],
        "split": "train"
    },
    {
        "image_url": "http://bhoomi.csa.iisc.ernet.in:8080/ihg/manuscript_editor/images/AAVARNI%20VYAKHYA/GOML/991/26.jpg",
        "label": "Character Line Segment",
        "instance_id": "http://bhoomi.csa.iisc.ernet.in:8080/ihg/manuscript_editor/images/AAVARNI%20VYAKHYA/GOML/991/26.jpg-1_3",
        "image_id": "http://bhoomi.csa.iisc.ernet.in:8080/ihg/manuscript_editor/images/AAVARNI%20VYAKHYA/GOML/991/26.jpg-1",
        "bbox": [
            218,
            75,
            2104,
            66
        ],
        "components": [
            {
                "bbox": [
                    218,
                    75,
                    2104,
                    66
                ],
                "poly": [
                    [
                        221,
                        77
                    ],
                    [
                        246,
                        75
                    ],
                    [
                        270,
                        77
                    ],
                    [
                        291,
                        77
                    ],
                    [
                        320,
                        77
                    ],
                    [
                        368,
                        81
                    ],
                    [
                        410,
                        80
                    ],
                    [
                        482,
                        83
                    ],
                    [
                        527,
                        85
                    ],
                    [
                        583,
                        86
                    ],
                    [
                        669,
                        88
                    ],
                    [
                        736,
                        85
                    ],
                    [
                        837,
                        84
                    ],
                    [
                        909,
                        84
                    ],
                    [
                        977,
                        85
                    ],
                    [
                        1039,
                        89
                    ],
                    [
                        1113,
                        96
                    ],
                    [
                        1206,
                        98
                    ],
                    [
                        1284,
                        97
                    ],
                    [
                        1370,
                        98
                    ],
                    [
                        1487,
                        92
                    ],
                    [
                        1543,
                        93
                    ],
                    [
                        1630,
                        95
                    ],
                    [
                        1815,
                        96
                    ],
                    [
                        1910,
                        89
                    ],
                    [
                        2006,
                        86
                    ],
                    [
                        2097,
                        88
                    ],
                    [
                        2216,
                        88
                    ],
                    [
                        2296,
                        88
                    ],
                    [
                        2321,
                        97
                    ],
                    [
                        2318,
                        108
                    ],
                    [
                        2303,
                        126
                    ],
                    [
                        2236,
                        138
                    ],
                    [
                        2113,
                        131
                    ],
                    [
                        2035,
                        129
                    ],
                    [
                        1834,
                        132
                    ],
                    [
                        1793,
                        133
                    ],
                    [
                        1686,
                        136
                    ],
                    [
                        1538,
                        135
                    ],
                    [
                        1421,
                        138
                    ],
                    [
                        1316,
                        136
                    ],
                    [
                        1217,
                        137
                    ],
                    [
                        1102,
                        140
                    ],
                    [
                        965,
                        126
                    ],
                    [
                        750,
                        122
                    ],
                    [
                        665,
                        123
                    ],
                    [
                        530,
                        121
                    ],
                    [
                        420,
                        119
                    ],
                    [
                        322,
                        117
                    ],
                    [
                        238,
                        117
                    ],
                    [
                        218,
                        112
                    ]
                ],
                "area": 277962.5
            }
        ],
        "split": "train"
    },
    {
        "image_url": "http://bhoomi.csa.iisc.ernet.in:8080/ihg/manuscript_editor/images/AAVARNI%20VYAKHYA/GOML/991/26.jpg",
        "label": "Character Line Segment",
        "instance_id": "http://bhoomi.csa.iisc.ernet.in:8080/ihg/manuscript_editor/images/AAVARNI%20VYAKHYA/GOML/991/26.jpg-1_4",
        "image_id": "http://bhoomi.csa.iisc.ernet.in:8080/ihg/manuscript_editor/images/AAVARNI%20VYAKHYA/GOML/991/26.jpg-1",
        "bbox": [
            239,
            121,
            2036,
            65
        ],
        "components": [
            {
                "bbox": [
                    239,
                    121,
                    2036,
                    65
                ],
                "poly": [
                    [
                        249,
                        137
                    ],
                    [
                        272,
                        124
                    ],
                    [
                        348,
                        131
                    ],
                    [
                        400,
                        121
                    ],
                    [
                        464,
                        125
                    ],
                    [
                        555,
                        128
                    ],
                    [
                        689,
                        132
                    ],
                    [
                        778,
                        128
                    ],
                    [
                        934,
                        132
                    ],
                    [
                        1010,
                        133
                    ],
                    [
                        1074,
                        141
                    ],
                    [
                        1163,
                        146
                    ],
                    [
                        1232,
                        143
                    ],
                    [
                        1349,
                        142
                    ],
                    [
                        1420,
                        141
                    ],
                    [
                        1483,
                        144
                    ],
                    [
                        1737,
                        140
                    ],
                    [
                        1872,
                        141
                    ],
                    [
                        1987,
                        136
                    ],
                    [
                        2190,
                        138
                    ],
                    [
                        2264,
                        141
                    ],
                    [
                        2274,
                        176
                    ],
                    [
                        1682,
                        182
                    ],
                    [
                        1596,
                        181
                    ],
                    [
                        1353,
                        184
                    ],
                    [
                        1255,
                        185
                    ],
                    [
                        948,
                        180
                    ],
                    [
                        543,
                        163
                    ],
                    [
                        426,
                        163
                    ],
                    [
                        384,
                        167
                    ],
                    [
                        324,
                        169
                    ],
                    [
                        269,
                        164
                    ],
                    [
                        239,
                        157
                    ],
                    [
                        240,
                        156
                    ]
                ],
                "area": 352003.5
            }
        ],
        "split": "train"
    },
    {
        "image_url": "http://bhoomi.csa.iisc.ernet.in:8080/ihg/manuscript_editor/images/AAVARNI%20VYAKHYA/GOML/991/26.jpg",
        "label": "Character Component",
        "instance_id": "http://bhoomi.csa.iisc.ernet.in:8080/ihg/manuscript_editor/images/AAVARNI%20VYAKHYA/GOML/991/26.jpg-1_5",
        "image_id": "http://bhoomi.csa.iisc.ernet.in:8080/ihg/manuscript_editor/images/AAVARNI%20VYAKHYA/GOML/991/26.jpg-1",
        "bbox": [
            231,
            165,
            543,
            45
        ],
        "components": [
            {
                "bbox": [
                    231,
                    165,
                    543,
                    45
                ],
                "poly": [
                    [
                        234,
                        171
                    ],
                    [
                        252,
                        165
                    ],
                    [
                        325,
                        173
                    ],
                    [
                        402,
                        172
                    ],
                    [
                        479,
                        172
                    ],
                    [
                        603,
                        172
                    ],
                    [
                        703,
                        172
                    ],
                    [
                        773,
                        189
                    ],
                    [
                        741,
                        201
                    ],
                    [
                        692,
                        208
                    ],
                    [
                        527,
                        209
                    ],
                    [
                        383,
                        208
                    ],
                    [
                        279,
                        204
                    ],
                    [
                        231,
                        196
                    ],
                    [
                        237,
                        185
                    ]
                ],
                "area": 104549.5
            }
        ],
        "split": "train"
    },
    {
        "image_url": "http://bhoomi.csa.iisc.ernet.in:8080/ihg/manuscript_editor/images/AAVARNI%20VYAKHYA/GOML/991/26.jpg",
        "label": "Physical Degradation",
        "instance_id": "http://bhoomi.csa.iisc.ernet.in:8080/ihg/manuscript_editor/images/AAVARNI%20VYAKHYA/GOML/991/26.jpg-1_6",
        "image_id": "http://bhoomi.csa.iisc.ernet.in:8080/ihg/manuscript_editor/images/AAVARNI%20VYAKHYA/GOML/991/26.jpg-1",
        "bbox": [
            1959,
            84,
            22,
            32
        ],
        "components": [
            {
                "bbox": [
                    1959,
                    84,
                    22,
                    32
                ],
                "poly": [
                    [
                        1959,
                        98
                    ],
                    [
                        1961,
                        94
                    ],
                    [
                        1970,
                        115
                    ],
                    [
                        1979,
                        111
                    ],
                    [
                        1980,
                        96
                    ],
                    [
                        1969,
                        84
                    ],
                    [
                        1959,
                        89
                    ]
                ],
                "area": 69049.0
            }
        ],
        "split": "train"
    },
    {
        "image_url": "http://bhoomi.csa.iisc.ernet.in:8080/ihg/manuscript_editor/images/AAVARNI%20VYAKHYA/GOML/991/26.jpg",
        "label": "Hole(Physical)",
        "instance_id": "http://bhoomi.csa.iisc.ernet.in:8080/ihg/manuscript_editor/images/AAVARNI%20VYAKHYA/GOML/991/26.jpg-1_7",
        "image_id": "http://bhoomi.csa.iisc.ernet.in:8080/ihg/manuscript_editor/images/AAVARNI%20VYAKHYA/GOML/991/26.jpg-1",
        "bbox": [
            752,
            90,
            73,
            66
        ],
        "components": [
            {
                "bbox": [
                    752,
                    90,
                    73,
                    66
                ],
                "poly": [
                    [
                        768,
                        99
                    ],
                    [
                        794,
                        90
                    ],
                    [
                        822,
                        111
                    ],
                    [
                        824,
                        138
                    ],
                    [
                        814,
                        150
                    ],
                    [
                        790,
                        155
                    ],
                    [
                        756,
                        143
                    ],
                    [
                        752,
                        127
                    ],
                    [
                        759,
                        108
                    ],
                    [
                        764,
                        105
                    ],
                    [
                        768,
                        102
                    ]
                ],
                "area": 51647.0
            }
        ],
        "split": "train"
    },
    {
        "image_url": "http://bhoomi.csa.iisc.ernet.in:8080/ihg/manuscript_editor/images/AAVARNI%20VYAKHYA/GOML/991/26.jpg",
        "label": "Hole(Physical)",
        "instance_id": "http://bhoomi.csa.iisc.ernet.in:8080/ihg/manuscript_editor/images/AAVARNI%20VYAKHYA/GOML/991/26.jpg-1_8",
        "image_id": "http://bhoomi.csa.iisc.ernet.in:8080/ihg/manuscript_editor/images/AAVARNI%20VYAKHYA/GOML/991/26.jpg-1",
        "bbox": [
            1744,
            98,
            61,
            60
        ],
        "components": [
            {
                "bbox": [
                    1744,
                    98,
                    61,
                    60
                ],
                "poly": [
                    [
                        1750,
                        112
                    ],
                    [
                        1774,
                        98
                    ],
                    [
                        1803,
                        109
                    ],
                    [
                        1804,
                        129
                    ],
                    [
                        1801,
                        148
                    ],
                    [
                        1777,
                        157
                    ],
                    [
                        1752,
                        151
                    ],
                    [
                        1744,
                        134
                    ],
                    [
                        1745,
                        117
                    ],
                    [
                        1749,
                        114
                    ]
                ],
                "area": 104322.5
            }
        ],
        "split": "train"
    },
    {
        "image_url": "http://bhoomi.csa.iisc.ernet.in:8080/ihg/manuscript_editor/images/AAVARNI%20VYAKHYA/GOML/991/26.jpg",
        "label": "Physical Degradation",
        "instance_id": "http://bhoomi.csa.iisc.ernet.in:8080/ihg/manuscript_editor/images/AAVARNI%20VYAKHYA/GOML/991/26.jpg-1_9",
        "image_id": "http://bhoomi.csa.iisc.ernet.in:8080/ihg/manuscript_editor/images/AAVARNI%20VYAKHYA/GOML/991/26.jpg-1",
        "bbox": [
            1179,
            52,
            18,
            16
        ],
        "components": [
            {
                "bbox": [
                    1179,
                    52,
                    18,
                    16
                ],
                "poly": [
                    [
                        1196,
                        57
                    ],
                    [
                        1190,
                        66
                    ],
                    [
                        1179,
                        67
                    ],
                    [
                        1179,
                        57
                    ],
                    [
                        1184,
                        52
                    ],
                    [
                        1189,
                        54
                    ],
                    [
                        1193,
                        55
                    ]
                ],
                "area": 18147.0
            }
        ],
        "split": "train"
    }
]